pyrwkv_tokenizer-0.9.1.dist-info/METADATA
pyrwkv_tokenizer-0.9.1.dist-info/WHEEL
pyrwkv_tokenizer-0.9.1.dist-info/licenses/LICENSE.txt
pyrwkv_tokenizer/rwkv_vocab_v20230424.txt
pyrwkv_tokenizer/__init__.py
pyrwkv_tokenizer/pyrwkv_tokenizer.cpython-312-powerpc64le-linux-gnu.so
pyrwkv_tokenizer-0.9.1.dist-info/RECORD
