Metadata-Version: 2.4
Name: pyrwkv_tokenizer
Version: 0.9.1
Classifier: Programming Language :: Rust
Classifier: Programming Language :: Python :: Implementation :: CPython
Classifier: Programming Language :: Python :: Implementation :: PyPy
Requires-Dist: pytest ; extra == 'dev'
Provides-Extra: dev
License-File: LICENSE.txt
Summary: RWKV Tokenizer
Keywords: LLM,RWKV,Language Model
Author: Cahya Wirawan <cahya.wirawan@gmail.com>
Author-email: Cahya Wirawan <cahya.wirawan@gmail.com>
License: Apache-2.0
Requires-Python: >=3.8
Project-URL: homepage, https://github.com/cahya-wirawan/rwkv-tokenizer
Project-URL: documentation, https://github.com/cahya-wirawan/rwkv-tokenizer
Project-URL: repository, https://github.com/cahya-wirawan/rwkv-tokenizer
Project-URL: changelog, https://github.com/cahya-wirawan/rwkv-tokenizer/blob/master/CHANGELOG.md
